{
    "os": "Linux-5.4.0-77-generic-x86_64-with-glibc2.31",
    "python": "3.9.5",
    "heartbeatAt": "2021-07-15T02:50:36.424393",
    "startedAt": "2021-07-15T02:50:25.383481",
    "docker": null,
    "gpu": "NVIDIA GeForce RTX 2080 Ti",
    "gpu_count": 2,
    "cpu_count": 12,
    "cuda": null,
    "args": [
        "--ip=127.0.0.1",
        "--stdin=9008",
        "--control=9006",
        "--hb=9005",
        "--Session.signature_scheme=\"hmac-sha256\"",
        "--Session.key=b\"628ab3fe-2f4c-4185-a03e-1e38f6befd68\"",
        "--shell=9007",
        "--transport=\"tcp\"",
        "--iopub=9009",
        "--f=/tmp/tmp-109821D7PMYr98r8di.json"
    ],
    "state": "running",
    "program": "<python with no main file>",
    "git": {
        "remote": "git@github.com:fredguth/nbdev_wandb_kaggle.git",
        "commit": "20f19f0873d788ed6ead6c0e44351b2a176b5582"
    },
    "email": "fredguth@fredguth.com",
    "root": "/home/fred/covid19",
    "host": "lisa-153",
    "username": "fred",
    "executable": "/home/fred/.conda/envs/covid19/bin/python"
}
